aedev/setup_hook.py
aedev_setup_hook-0.3.6.dist-info/LICENSE.md
aedev_setup_hook-0.3.6.dist-info/METADATA
aedev_setup_hook-0.3.6.dist-info/WHEEL
aedev_setup_hook-0.3.6.dist-info/top_level.txt
aedev_setup_hook-0.3.6.dist-info/zip-safe
aedev_setup_hook-0.3.6.dist-info/RECORD
